{
  "schemaVersion": 1,
  "scanner": {
    "version": "1.0.0",
    "rules": "19f6a1b4a518"
  },
  "target": {
    "kind": "url",
    "ref": "https://mcp.thechrisgrey.com"
  },
  "scannedAt": "2026-07-16T16:30:54.546Z",
  "durationMs": 375,
  "layers": {
    "metadata": true,
    "static": false
  },
  "tools": [
    {
      "name": "search_blog",
      "descriptionHash": "38994312b69d038987c0f120562a0502aed7ff1cb99a4780bc308d64a3920916"
    },
    {
      "name": "get_blog_post",
      "descriptionHash": "67a0d991a4fc5a370648c9084f5531816902eff9a76ad7a99a389d11962840d1"
    },
    {
      "name": "ask_alti",
      "descriptionHash": "618fa030fa181a617c151f54553bad05ed30257ad1853fb71dfea0bd1971b392"
    }
  ],
  "findings": [],
  "score": 100,
  "scoreBreakdown": {},
  "errors": []
}