{
  "schemaVersion": 1,
  "scanner": {
    "version": "1.6.0",
    "rules": "402995650b68"
  },
  "target": {
    "kind": "url",
    "ref": "https://entity-resolve.x402supply.com/mcp"
  },
  "scannedAt": "2026-07-22T06:45:23.861Z",
  "durationMs": 581,
  "layers": {
    "metadata": true,
    "static": false
  },
  "tools": [
    {
      "name": "resolve",
      "descriptionHash": "592e935f4ef8a3393c29b41fe89766700e478b08cbd633e71aee150078366f46",
      "description": "Fuzzy-dedupe a list of records into clusters of likely-duplicate entities. Blocks by normalized token prefix, scores with Jaro-Winkler + token-set matching (exact on email/phone), unions matches above threshold, and returns a merged canonical record per cluster with a confidence score. Deterministic",
      "labels": [
        "untrusted-content",
        "private-data",
        "public-sink"
      ]
    }
  ],
  "findings": [
    {
      "id": "MCP-TOXIC-FLOW-001",
      "severity": "high",
      "category": "toxic-flow",
      "title": "Lethal trifecta: untrusted input + private data + external sink",
      "detail": "Server \"mcp\" exposes tools that together enable an exfiltration flow. Untrusted content: resolve · Private data: resolve · Public sink: resolve.",
      "evidence": {
        "source": "server:mcp",
        "snippet": "Untrusted content: resolve · Private data: resolve · Public sink: resolve"
      },
      "confidence": 0.6,
      "remediation": "Do not co-install these capabilities under one trust boundary; an injected comment/email can steer the model to exfiltrate via the sink tool."
    }
  ],
  "score": 80,
  "scoreBreakdown": {
    "toxic-flow": 20
  },
  "errors": []
}