{
  "schemaVersion": 1,
  "scanner": {
    "version": "1.0.0",
    "rules": "19f6a1b4a518"
  },
  "target": {
    "kind": "url",
    "ref": "https://evidence.dropwatchhq.com/mcp"
  },
  "scannedAt": "2026-07-16T16:35:27.740Z",
  "durationMs": 212,
  "layers": {
    "metadata": true,
    "static": false
  },
  "tools": [
    {
      "name": "build_evidence_pack",
      "descriptionHash": "40eb7263e98dc865ee077f2a223144487ce3a40d567dc471a1ad0b085b75dcd3"
    },
    {
      "name": "ground_claim",
      "descriptionHash": "370ec36fbe4d23397b54aa34d610778fe06baf09b2ce0db1937f5835d63bbf4e"
    },
    {
      "name": "screen_entity",
      "descriptionHash": "1471552a57e43a7dce43292d37bd0fb34a28f46b46055fc8e429b296dde99cc6"
    },
    {
      "name": "verify_pack",
      "descriptionHash": "835caa3e8c323e0f2b198449edf025437e8a2f382576af802cf1d3f8a5a91468"
    }
  ],
  "findings": [],
  "score": 100,
  "scoreBreakdown": {},
  "errors": []
}