{
  "schemaVersion": 1,
  "scanner": {
    "version": "1.0.0",
    "rules": "19f6a1b4a518"
  },
  "target": {
    "kind": "url",
    "ref": "https://mcp.ecoexperten.com/mcp"
  },
  "scannedAt": "2026-07-16T16:30:51.645Z",
  "durationMs": 1680,
  "layers": {
    "metadata": true,
    "static": false
  },
  "tools": [
    {
      "name": "energieausweis_info",
      "descriptionHash": "9644cc086b8f97c051dbbc47a523c0d87e71b73742c8540e720d46817e8bd887"
    },
    {
      "name": "bestellung_pruefen",
      "descriptionHash": "c6aafd124301eda8c1815f56a063bf05dfeb8913d66cb629ceadbe82938539da"
    },
    {
      "name": "bestellung_aufgeben",
      "descriptionHash": "d6328ecbc592dabee64964e88e7ef7fa5b3e75f502e84a89e5ed9a3c97f594c8"
    },
    {
      "name": "bestell_status",
      "descriptionHash": "58da0dfbdf804b180dc54d5eed7af8762a6aeb3988564c3d389ea73cbe7ea6a1"
    }
  ],
  "findings": [],
  "score": 100,
  "scoreBreakdown": {},
  "errors": []
}