{
  "schemaVersion": 1,
  "scanner": {
    "version": "1.6.0",
    "rules": "402995650b68"
  },
  "target": {
    "kind": "url",
    "ref": "https://app.daedalmap.com/mcp/currency"
  },
  "scannedAt": "2026-07-21T06:49:28.571Z",
  "durationMs": 173,
  "layers": {
    "metadata": true,
    "static": false
  },
  "tools": [
    {
      "name": "get_catalog",
      "descriptionHash": "e4fbcea606c37a66b15e3d3618ef87832edec60a3df9c22f722946bd3337a271",
      "description": "Free discovery. Returns the list of live agent-ready data packs available on DaedalMap."
    },
    {
      "name": "get_pack",
      "descriptionHash": "004d34a6d3d5ac3743b35b3fd1899fa7fb9aef0c8b836a702b40eecd237ed3d7",
      "description": "Free discovery. Returns detailed metadata, coverage, freshness, preferred canonical tool guidance, and first-query examples for one pack. Call this before querying a new pack so you can see time shape, coverage limits, and the paste-ready first query."
    },
    {
      "name": "get_fx_rates",
      "descriptionHash": "25b4ebee5c8210e30a9d234a5adcfd46401e46336bd7029f209ab10eb3817c67",
      "description": "Free tool. Queries the currency pack using filters.region_ids plus filters.time.granularity to return daily, weekly, or monthly FX data."
    }
  ],
  "findings": [],
  "score": 100,
  "scoreBreakdown": {},
  "errors": []
}