{
  "schemaVersion": 1,
  "scanner": {
    "version": "1.0.0",
    "rules": "19f6a1b4a518"
  },
  "target": {
    "kind": "url",
    "ref": "https://mcp.stackoverflow.com"
  },
  "scannedAt": "2026-07-16T16:30:52.299Z",
  "durationMs": 170,
  "layers": {
    "metadata": false,
    "static": false
  },
  "findings": [],
  "score": 100,
  "scoreBreakdown": {},
  "errors": [
    {
      "scanner": "metadata",
      "message": "Streamable HTTP error: Error POSTing to endpoint: {\"type\":\"https://httpstatuses.io/401\",\"title\":\"Unauthorized\",\"status\":401,\"traceId\":\"00-ddd798232ad7731166bdb38cd1369073-9122dd08f217e7c4-01\"}"
    }
  ]
}