{
  "schemaVersion": 1,
  "scanner": {
    "version": "1.6.0",
    "rules": "402995650b68"
  },
  "target": {
    "kind": "url",
    "ref": "https://www.xfish.hu/app/mcpapi.php"
  },
  "scannedAt": "2026-07-18T06:23:06.380Z",
  "durationMs": 2865,
  "layers": {
    "metadata": true,
    "static": false
  },
  "tools": [
    {
      "name": "search_products",
      "descriptionHash": "17e083262f37af0ed877d9faf01ebcf6bff557d1c5954b2c16841369aa22af13",
      "description": "Termékkereső az XFish.hu horgász webáruházban. Keresés szöveg, kategória, gyártó, márka, ár és készlet alapján. Magyar és angol keresés is működik."
    },
    {
      "name": "get_categories",
      "descriptionHash": "4b01a52bebc0bb82bc00641f761ac8f8c2252bab6ae4973258543ac68b8144ec",
      "description": "Kategóriák listázása az XFish.hu webáruházból. Visszaadja a kategóriafát: ID, név, szülő, termékszám."
    },
    {
      "name": "get_product_details",
      "descriptionHash": "c4ae3ade21ad2cde90e76264dea5eb11948b69ef7d27b0878b140242fb7d635c",
      "description": "Egy adott termék részletes adatainak lekérdezése: név, ár, leírás, készlet, kép, gyártó, cikkszám."
    },
    {
      "name": "get_manufacturers",
      "descriptionHash": "bf3714cb113d529287e3ef2fb50d9ae0742aa276e091d61ad414fedc42be9cc3",
      "description": "Gyártók/márkák listázása az XFish.hu webáruházból. Visszaadja a gyártó ID-kat, amelyek a search_products manufacturer_id paraméteréhez szükségesek."
    }
  ],
  "findings": [],
  "score": 100,
  "scoreBreakdown": {},
  "errors": []
}