{
  "schemaVersion": 1,
  "scanner": {
    "version": "1.0.0",
    "rules": "19f6a1b4a518"
  },
  "target": {
    "kind": "url",
    "ref": "https://tech-enrichment.api.klymax402.com/mcp"
  },
  "scannedAt": "2026-07-16T16:31:47.870Z",
  "durationMs": 1396,
  "layers": {
    "metadata": true,
    "static": false
  },
  "tools": [
    {
      "name": "website_detect_tech_stack",
      "descriptionHash": "1db4cd563bbe1d2ab0856a4b6a716376a20184f36d4ae3af93949be2d73e26e2"
    }
  ],
  "findings": [],
  "score": 100,
  "scoreBreakdown": {},
  "errors": []
}