{
  "schemaVersion": 1,
  "scanner": {
    "version": "1.6.0",
    "rules": "402995650b68"
  },
  "target": {
    "kind": "url",
    "ref": "https://mcp.venture.caplia.ai/"
  },
  "scannedAt": "2026-07-21T06:50:33.420Z",
  "durationMs": 683,
  "layers": {
    "metadata": true,
    "static": false
  },
  "tools": [
    {
      "name": "caplia_search",
      "descriptionHash": "268b1b03ad22654bf904be86ff83141e50981c9412d5f207584cf81f48933432",
      "description": "Search Caplia for companies in the caller's pipeline by name. Returns up to 25 matches with id, name, website, industry, and stage. Use this to find a company before fetching its full profile."
    },
    {
      "name": "caplia_list_companies",
      "descriptionHash": "66c5cc6c56e7788f922a963361285f5e634c4ba16bf3d90719216698b16d4a19",
      "description": "List companies in the caller's pipeline. Supports cursor pagination (`cursor` from the previous response's `next_cursor`) and filtering by `stage` or by named `view`. Use `limit` (default 25, max 100) to bound the page size."
    },
    {
      "name": "caplia_get_company",
      "descriptionHash": "c728fd9fb5effeb2fbf03b3967a9c81cfe3fe8ee58e560e8317aef3934087f6a",
      "description": "Fetch the full profile of one company by UUID: name, problem statement, industry, stage, website, founders, fundraising round, etc."
    },
    {
      "name": "caplia_get_company_scores",
      "descriptionHash": "ceeed5b4a36bcbaf4e4b8e2333c9862938973e6e094dd9f5bdcb1fcd8d4fdea1",
      "description": "Get the CRI score and per-thesis match scores for a company. Returns `{ cri: { score, scored_at, domains }, thesis_matches: [...] }`. Useful when an agent needs to reason about how a company fits the team's investment theses."
    },
    {
      "name": "caplia_get_company_metrics",
      "descriptionHash": "c241937f3a8fc95e5596d63279d3fa8893041fb0cff9242ef2e1f8a222608437",
      "description": "Get traction and key metrics for a company: revenue, growth, headcount, fundraising round milestones, etc."
    },
    {
      "name": "caplia_list_company_documents",
      "descriptionHash": "113eb68132a6ce1118fcdeeb7faa6949eea39b5a753ad4b001c4c6e8a1417977",
      "description": "List all data-room documents attached to a company: pitch decks, financial models, founder updates, term sheets. Each entry has id, name, folder, type, size, and created_at.",
      "labels": [
        "private-data"
      ]
    },
    {
      "name": "caplia_get_document_url",
      "descriptionHash": "405ea5e3bd40f4a186487c613b44c75de45814cdfcdc9c361a154ae8eef0b348",
      "description": "Get a 1-hour signed download URL for a specific data-room document. The agent can fetch the bytes directly from the returned URL — file content does not pass through the API.",
      "labels": [
        "untrusted-content",
        "private-data"
      ]
    },
    {
      "name": "caplia_list_theses",
      "descriptionHash": "250ba0e6f56458f578271f1462561af37ebcde0a58d06b154542a6c339a3f6dc",
      "description": "List the team's active investment theses with their descriptions. Useful for an agent that's reasoning about whether a deal fits a thesis."
    },
    {
      "name": "caplia_list_properties",
      "descriptionHash": "3103baa438a0c78999651ba11775c0d1ea5593da90e0bba70b03947f45d0ab71",
      "description": "List the team's custom properties (e.g. an awards programme's \"Award Category\") with their selectable options. Properties are configured per team inside Caplia, so call this before caplia_submit_deck when you want to tag a submission — pass selections via its `properties` argument using the option i"
    },
    {
      "name": "caplia_list_views",
      "descriptionHash": "5843b2e42b9c97c068c4ec9d2f1c3b4aaadab53a20fc7db08b95c9d8a80da28f",
      "description": "List the team's configured pipeline views (e.g. Deal Flow, My Pipeline, Screening). Each view has a key that can be used as the `view` argument on caplia_list_companies."
    },
    {
      "name": "caplia_get_view_companies",
      "descriptionHash": "7d779f0b13803b527536bfba917a634132a46a64f585a0bac44d4615b9db5b4e",
      "description": "Fetch the companies belonging to a named pipeline view (e.g. `deal-flow`, `my-pipeline`)."
    },
    {
      "name": "caplia_get_job",
      "descriptionHash": "9886e9d797036a59e5aec3d1d7dbe32a9caca0871186696163167b83610c845a",
      "description": "Poll the status of an async job (typically the result of a deck submission). Returns `{ status, company_id, results, errors }`. Recommended polling cadence: every 3 seconds."
    },
    {
      "name": "caplia_submit_deck",
      "descriptionHash": "7cb90537ae2e79fed228f94a1b7c83b010e2a5872e1a03687bbb98714662bbdb",
      "description": "Submit a pitch deck (PDF) to the caller's Caplia pipeline. The deck flows through the same intake pipeline as web uploads and email forwards: text extraction → company shell creation → CRI scoring → thesis matching. Returns `{ job_id, status: \"queued\", poll_url }` immediately; use `caplia_get_job` w",
      "labels": [
        "public-sink"
      ]
    }
  ],
  "findings": [
    {
      "id": "MCP-TOXIC-FLOW-001",
      "severity": "high",
      "category": "toxic-flow",
      "title": "Lethal trifecta: untrusted input + private data + external sink",
      "detail": "Server \"mcp.venture.caplia.ai\" exposes tools that together enable an exfiltration flow. Untrusted content: caplia_get_document_url · Private data: caplia_list_company_documents, caplia_get_document_url · Public sink: caplia_submit_deck.",
      "evidence": {
        "source": "server:mcp.venture.caplia.ai",
        "snippet": "Untrusted content: caplia_get_document_url · Private data: caplia_list_company_documents, caplia_get_document_url · Public sink: caplia_submit_deck"
      },
      "confidence": 0.6,
      "remediation": "Do not co-install these capabilities under one trust boundary; an injected comment/email can steer the model to exfiltrate via the sink tool."
    }
  ],
  "score": 80,
  "scoreBreakdown": {
    "toxic-flow": 20
  },
  "errors": []
}