{
  "schemaVersion": 1,
  "scanner": {
    "version": "1.5.0",
    "rules": "402995650b68"
  },
  "target": {
    "kind": "url",
    "ref": "https://us-central1-minoa-roi-firebase.cloudfunctions.net/endpoints-mcp"
  },
  "scannedAt": "2026-07-17T10:09:26.398Z",
  "durationMs": 147,
  "layers": {
    "metadata": false,
    "static": false
  },
  "findings": [],
  "score": 100,
  "scoreBreakdown": {},
  "errors": [
    {
      "scanner": "metadata",
      "message": "Streamable HTTP error: Error POSTing to endpoint: {\"error\":{\"code\":-32001,\"data\":{\"authorization_metadata\":\"https://us-central1-minoa-roi-firebase.cloudfunctions.net/endpoints-mcp/.well-known/oauth-authorization-server\",\"error\":\"unauthorized\",\"error_description\":\"Missing or invalid Authorization header\"},\"message\":\"Authentication required\"},\"id\":null,\"jsonrpc\":\"2.0\"}"
    }
  ]
}