{
  "schemaVersion": 1,
  "scanner": {
    "version": "1.6.0",
    "rules": "402995650b68"
  },
  "target": {
    "kind": "url",
    "ref": "https://sense2.com.au/api/mcp"
  },
  "scannedAt": "2026-07-19T06:46:24.261Z",
  "durationMs": 921,
  "layers": {
    "metadata": true,
    "static": false
  },
  "tools": [
    {
      "name": "search_products",
      "descriptionHash": "6cd2433f8e9a48d3fa3a6d3c930e071bee5102be16376fd353acdc77f4f145df",
      "description": "Search Sense2 promotional product catalogue by keyword"
    },
    {
      "name": "get_product",
      "descriptionHash": "b2bc2163ab8b0e3e5bdaf1b91cb92f46eabc16b2bdd54e33dc73571c0826e7db",
      "description": "Get full product details by PID"
    },
    {
      "name": "get_quote",
      "descriptionHash": "2f2ba6996dbd7970e6decd37b913919451c7e03ac424300654f7b4e9d59936d4",
      "description": "Get a pricing quote for a product at a specific quantity"
    },
    {
      "name": "get_categories",
 64c9ca2bcc"
    }
  ],
  "findings": [],
  "score": 100,
  "scoreBreakdown": {},
  "errors": []
}  "description": "List all product categories with product counts"
    },
    {
      "name": "get_industries",
      "descriptionHash": "ed13232093432a558dc6b86ae6d89b2c61d75e0d09c6dc67a6fa8264c9ca2bcc",
      "description": "List all industry affinities with product counts"
    }
  ],
  "findings": [],
  "score": 100,
  "scoreBreakdown": {},
  "errors": []
}0ad513339b2596751f02d3ad957ec1202dfcd76dd1abc4f7d",
      "description": "List all 12 Shop by Aesthetic editorial collections (Quiet Luxury, Scandinavian, Coastal, etc.) with product counts and URLs",
      "labels": [
        "untrusted-content"
      ]
    },
    {
      "name": "get_intents",
      "descriptionHash": "1cf0e88ac7541d4167c8435408be87a845cf158bff60e91d98aca7a626b6b82a",
      "description": "List all 30 Shop by Intent curated collections (VIP client gifts, conference swag, onboarding kits, etc.) with product counts and URLs",
      "labels": [
        "untrusted-content"
      ]
    },
    {
      "name": "get_brands",
      "descriptionHash": "334cddb497f91f3eff7a63c76ecd617ae8d71ddf3fe55013729037f28ac8ee1b",
      "description": "List all 107 Sense2 case-study brands (Google, Nike, Mercedes, Porsche, MasterCard, etc.) with industry, headline, and URL",
      "labels": [
        "untrusted-content"
      ]
    },
    {
      "name": "get_brand",
      "descriptionHash": "07267bd9df01351713c7df370405b228a7b656da951a4afbe011235c6b5d7110",
      "description": "Get full brand case-study details by slug (story, signature, logo tagline, industries)"
    },
    {
      "name": "get_100_best",
      "descriptionHash": "e58bc4a966f8cb68062d1594c303166ed23ca903a273db8c13f89f11913dd9c7",
      "description": "The 100 Best Promotional Products in Australia - Sense2 quarterly flagship edit, 10 sections x 10 products with editorial intros"
    },
    {
      "name": "get_inspirations",
      "descriptionHash": "dc58282ceb3ca49911bb976575734506a00b3c162db5d7233b8d25fc63ed8811",
      "description": "List Sense2 editorial inspiration cards (brand-crushes - visual merchandising ideas from real brands, with Findie creative insights)"
    },
    {
      "name": "get_inspiration",
      "descriptionHash": "5f3da395a6a0f94032b4eff974c5df7f13d12b65561cf81ea68c78ff9c95da96",
      "description": "Get a single inspiration card by slug (full creative insight, signature move, brand vibe)"
    },
    {
      "name": "get_brand_moves",
      "descriptionHash": "abbd766d4f694f4296734ea5a9e2c285f400bbb80ca0e3692de0346730de745d",
      "description": "The 12 Sense2 Brand Moves — practical creative strategy ideas for branded merchandise (Own One Colour, Brand the Ritual, Make Texture the Hero, etc.) plus the Combining Aesthetics framework (70/20/10 rule with suggested pairings)"
    },
    {
      "name": "get_100_best_intel",
      "descriptionHash": "3a67336a1a7c2e8f4cf57c5105eaa55a4f518c87fda567a57eedb8364ba7c3a6",
      "description": "The Sense2 100 editorial intelligence layer — the six Sense2 Standard lenses (Desirability, Everyday relevance, Brandability, Perceived value, Retention potential, Story value), the Retention Test, 2026 market insights, How to Use guide by outcome (awareness, belonging, gratitude, modernity, culture"
    }
  ],
  "findings": [],
  "score": 100,
  "scoreBreakdown": {},
  "errors": []
}