{
  "schemaVersion": 1,
  "scanner": {
    "version": "1.0.0",
    "rules": "19f6a1b4a518"
  },
  "target": {
    "kind": "url",
    "ref": "https://mcp.cometchat.com/mcp"
  },
  "scannedAt": "2026-07-16T16:31:51.361Z",
  "durationMs": 272,
  "layers": {
    "metadata": true,
    "static": false
  },
  "tools": [
    {
      "name": "search_cometchat_docs",
      "descriptionHash": "0f04e87e2799d0a14975a972dddd4f50fab99d4d5698c13a265af7e2a75ee57d"
    },
    {
      "name": "fetch_cometchat_doc_page",
      "descriptionHash": "2dd39557cf46744f220d866ae998680bb27ce6e32b9237836a18402e03f74db0"
    },
    {
      "name": "get_cometchat_implementation_bundle",
      "descriptionHash": "0a6caef3312423bcf687eb60fd7f4b3430e47e97285515e058735195547a9e5c"
    }
  ],
  "findings": [],
  "score": 100,
  "scoreBreakdown": {},
  "errors": []
}