{
  "schemaVersion": 1,
  "scanner": {
    "version": "1.0.0",
    "rules": "19f6a1b4a518"
  },
  "target": {
    "kind": "npm",
    "ref": "kairos-astrology",
    "resolvedVersion": "1.1.0"
  },
  "scannedAt": "2026-07-16T16:33:58.759Z",
  "durationMs": 1221,
  "layers": {
    "metadata": false,
    "static": true
  },
  "findings": [
    {
      "id": "MCP-EXFIL-002",
      "severity": "low",
      "category": "exfiltration",
      "title": "Hardcoded public IP address",
      "detail": "Source hardcodes public IP 1.2.3.4. Verify it is not an exfiltration destination.",
      "evidence": {
        "source": "web/engine.js",
        "snippet": "1.2.3.4",
        "line": 32
      },
      "confidence": 0.3
    },
    {
      "id": "MCP-EXFIL-002",
      "severity": "low",
      "category": "exfiltration",
      "title": "Hardcoded public IP address",
      "detail": "Source hardcodes public IP 4.5.6.7. Verify it is not an exfiltration destination.",
      "evidence": {
        "source": "web/engine.js",
        "snippet": "4.5.6.7",
        "line": 32
      },
      "confidence": 0.3
    },
    {
      "id": "MCP-CAP-002",
      "severity": "medium",
      "category": "capability",
      "title": "Executes shell commands",
      "detail": "Executes shell commands in web/engine.js. Confirm this is disclosed by the server's tool descriptions.",
      "evidence": {
        "source": "web/engine.js",
        "snippet": "exec(",
        "line": 531
      },
      "confidence": 0.5
    }
  ],
  "score": 88,
  "scoreBreakdown": {
    "exfiltration": 5,
    "capability": 8
  },
  "errors": []
}