{
  "schemaVersion": 1,
  "scanner": {
    "version": "1.6.0",
    "rules": "402995650b68"
  },
  "target": {
    "kind": "url",
    "ref": "https://web-production-ae61.up.railway.app/mcp/lifestyle-medicine-knowledge"
  },
  "scannedAt": "2026-07-17T17:05:14.511Z",
  "durationMs": 548,
  "layers": {
    "metadata": true,
    "static": false
  },
  "tools": [
    {
      "name": "lifestyle_query",
      "descriptionHash": "37dff0161c9afc1afc1ec1616898744c7a3e195746e25b1f742b2cc4199220da",
      "description": "Ask any lifestyle medicine question. Returns evidence-based answer with citations from a 200-chunk knowledge base spanning ACLM 6-pillars, B.O.N.S.A.I. nutrition, drug-food interactions, lab interpretation, GLP guidance, wearables, and CGM signal interpretation."
    }
  ],
  "findings": [],
  "score": 100,
  "scoreBreakdown": {},
  "errors": []
}