{
  "schemaVersion": 1,
  "scanner": {
    "version": "1.6.0",
    "rules": "402995650b68"
  },
  "target": {
    "kind": "url",
    "ref": "https://mcp.apify.com/?actors=prometheusagency/bluesky-brand-monitor"
  },
  "scannedAt": "2026-07-17T17:05:12.737Z",
  "durationMs": 110,
  "layers": {
    "metadata": false,
    "static": false
  },
  "findings": [],
  "score": 100,
  "scoreBreakdown": {},
  "errors": [
    {
      "scanner": "metadata",
      "message": "Streamable HTTP error: Error POSTing to endpoint: {\"error\":\"invalid_token\",\"error_description\":\"Missing or invalid access token. Pass an Apify API token in the Authorization: Bearer <token> header. Manage tokens at https://console.apify.com/account/integrations\"}"
    }
  ]
}