{
  "schemaVersion": 1,
  "scanner": {
    "version": "1.6.0",
    "rules": "402995650b68"
  },
  "target": {
    "kind": "url",
    "ref": "https://mcp.barwa.pl/mcp"
  },
  "scannedAt": "2026-07-24T06:46:08.108Z",
  "durationMs": 2152,
  "layers": {
    "metadata": true,
    "static": false
  },
  "tools": [
    {
      "name": "list_products",
      "descriptionHash": "5141a62cbde440432690bf3b1c19e44ee92c56c970a446f2bd6bb0d46e911c90",
      "description": "List printing products available at the barwa.pl online print shop (business cards,\nflyers, posters, stickers, books, etc.) with links. Prices are obtained per product\nvia get_quote — call that with a product's slug."
    },
    {
      "name": "get_product_pricing_schema",
      "descriptionHash": "11dcc9e9f7c7073929ab39f56ef69945ddc18d12874ca4f703fbe330ed1a7176",
      "description": "Get the full set of quotable parameters for a barwa.pl product: allowed sizes/formats,\nquantity limits, materials, single/double-sided option, page-count limits and available\nfinishes (marking which are mandatory). Call before get_quote to know valid option ids."
    },
    {
      "name": "recommend_product",
      "descriptionHash": "341ad192800d0a9742f777b64f12ca8e107fdfc672ec71adfed6b69ea3b0169b",
      "description": "Recommend barwa.pl products matching a described customer need (e.g. \"something for a\ntrade fair\", \"gift packaging\"). Returns matching products with links; price them with\nget_quote. If empty, ask the customer to clarify the need."
    },
    {
      "name": "get_quote",
      "descriptionHash": "7db9a144c2f50f6006bee3c65a9335fa6d4f2f265ddeff1ab6af35da34ff1419",
      "description": "Get a price quote for a barwa.pl product. Calculated by the same engine as the on-site\ncalculator, so the price is identical. Returns net/gross price, currency, delivery time and,\nif the configuration matches a defined product, its name and link. Use get_product_pricing_schema\nfirst for valid option"
    },
    {
      "name": "get_shipping_info",
      "descriptionHash": "eb20200c22c300d601f1a9243669a1f3e98019aa179ad61a86b5916adc9f9588",
      "description": "Get shipping cost thresholds (by order weight) and the free-shipping threshold for the\nshop's country, in the shop currency."
    },
    {
      "name": "get_file_specs",
      "descriptionHash": "1ff4095163d81925e155ee03972ca23a42a53b6323246886f59bfe4c30ae153e",
      "description": "Get print-file preparation requirements for a barwa.pl product (format, color mode,\nresolution, bleed) plus a link to the how-to-prepare guide.",
      "labels": [
        "private-data",
        "destructive"
      ]
    }
  ],
  "findings": [],
  "score": 100,
  "scoreBreakdown": {},
  "errors": []
}