{
  "schemaVersion": 1,
  "scanner": {
    "version": "1.4.0",
    "rules": "a1c0c9e6130b"
  },
  "target": {
    "kind": "url",
    "ref": "https://solana-mcp.tenzro.xyz/mcp"
  },
  "scannedAt": "2026-07-17T09:38:21.470Z",
  "durationMs": 852,
  "layers": {
    "metadata": true,
    "static": false
  },
  "tools": [
    {
      "name": "solana_get_balance",
      "descriptionHash": "60306572ae9d9b11e1243735e618d0f2a70f06c448d9a8100e6177ce8cfbcbee",
      "description": "Get the native SOL balance of a Solana wallet address",
      "labels": [
        "private-data"
      ]
    },
    {
      "name": "solana_get_nft",
      "descriptionHash": "5c765027aa0e18b4a02a9c4fd02af1edbdd44b97ab0623b1fd2487880f2e4f3b",
      "description": "Get NFT metadata using the Metaplex DAS (Digital Asset Standard) API. Requires a Helius API key set via HELIUS_API_KEY env var, or returns the call pattern for manual use.",
      "labels": [
        "private-data"
      ]
    },
    {
      "name": "solana_get_nfts_by_owner",
      "descriptionHash": "752438968590be92673c3869786e8d34887d3ed564c6c9d9557b969fa05a7e11",
      "description": "Get all NFTs (compressed and standard) owned by a Solana address using the Metaplex DAS API. Requires HELIUS_API_KEY env var.",
      "labels": [
        "private-data"
      ]
    },
    {
      "name": "solana_get_price",
      "descriptionHash": "b21a5b7f0e0e8628a1d4915b4f5b7a6f0b3df982b3a9295cf0c782c4e1531232",
      "description": "Get the current USD price of a Solana token from Jupiter Price API v3. Requires the token mint address (e.g. 'So11111111111111111111111111111111111111112' for SOL).",
      "labels": [
        "private-data"
      ]
    },
    {
      "name": "solana_get_slot",
      "descriptionHash": "ef4d019f91010e20bd9b31681e3ad83bc7d11d1c8a34920e7074cc37c5186915",
      "description": "Get the current slot height of the Solana network"
    },
    {
      "name": "solana_get_token_accounts",
      "descriptionHash": "27abd674e80fee29620168e3cfa1eac3aaa2a3bf5d663ce8200586b35dbec897",
      "description": "Get all SPL token accounts owned by a Solana wallet address, including balances and mint addresses",
      "labels": [
        "private-data"
      ]
    },
    {
      "name": "solana_get_token_info",
      "descriptionHash": "79e87821c237651dde7f1e20b9b73a015dfb006d3e4733993ce42a31d5882a78",
      "description": "Get metadata for an SPL token by its mint address, including name, symbol, decimals, and logo from the Jupiter token list",
      "labels": [
        "private-data"
      ]
    },
    {
      "name": "solana_get_tps",
      "descriptionHash": "4b652d3f7af84c7d83e58ed69bb4760336d2544127a94b6edeed9354607c9db2",
      "description": "Get the current transactions per second (TPS) on the Solana network by sampling recent performance data"
    },
    {
      "name": "solana_get_transaction",
      "descriptionHash": "439b9766ebda3a53a9a80702a66c259a9948dba8f8fffd600c72896e98b1c348",
      "description": "Get details of a Solana transaction by its signature, including status, block time, and instructions"
    },
    {
      "name": "solana_get_yield",
      "descriptionHash": "d084b7510969659641a1505e56a7afdd3e5d8d2b457f272a039524e142c23042",
      "description": "Get current yield/APY information for Solana DeFi staking protocols including Marinade, Jito, BlazeStake, and native staking"
    },
    {
      "name": "solana_resolve_domain",
      "descriptionHash": "e2bbb3b45bd4c7e4b6f9a4c9a9988b6907363ebdf06a9ba4e313c65ce79fad55",
      "description": "Resolve a .sol (Solana Name Service) domain to its owner wallet address using the Bonfida SNS proxy",
      "labels": [
        "private-data"
      ]
    },
    {
      "name": "solana_stake",
      "descriptionHash": "549ab0beab371d1cf8fdf1f0821ff8b1f3aadf01de1ced076c4d69ba9cc33cfe",
      "description": "Get instructions for staking SOL with a validator. Returns the step-by-step process (does not execute the transaction).",
      "labels": [
        "destructive"
      ]
    },
    {
      "name": "solana_swap",
      "descriptionHash": "b3a2ddf848de4db12a4af42a9fa135c2480fa376e86fd43642667d051239e97e",
      "description": "Get a swap quote from Jupiter aggregator for trading between two Solana tokens. Returns route, price impact, and estimated output amount.",
      "labels": [
        "private-data"
      ]
    },
    {
      "name": "solana_transfer",
      "descriptionHash": "3826db83c977e2329e3a86ca9698075872703db98c0966a8c018b04e29343413",
      "description": "Get instructions for transferring SOL between two addresses. Returns the transaction structure (does not execute).",
      "labels": [
        "destructive"
      ]
    }
  ],
  "findings": [
    {
      "id": "MCP-TOOL-POISON-003",
      "severity": "high",
      "category": "tool-poisoning",
      "title": "Description references secrets/credentials",
      "detail": "Description of \"solana_get_nft\" references sensitive artifacts (env var, api_key). A tool description has no reason to mention credentials.",
      "evidence": {
        "source": "tool:solana_get_nft",
        "snippet": "Get NFT metadata using the Metaplex DAS (Digital Asset Standard) API. Requires a Helius API key set via HELIUS_API_KEY env var, or returns the call pattern for …"
      },
      "confidence": 0.65
    },
    {
      "id": "MCP-TOOL-POISON-003",
      "severity": "high",
      "category": "tool-poisoning",
      "title": "Description references secrets/credentials",
      "detail": "Description of \"solana_get_nfts_by_owner\" references sensitive artifacts (env var, api_key). A tool description has no reason to mention credentials.",
      "evidence": {
        "source": "tool:solana_get_nfts_by_owner",
        "snippet": "Get all NFTs (compressed and standard) owned by a Solana address using the Metaplex DAS API. Requires HELIUS_API_KEY env var."
      },
      "confidence": 0.65
    }
  ],
  "score": 70,
  "scoreBreakdown": {
    "tool-poisoning": 30
  },
  "errors": []
}}idence": 0.65
    }
  ],
  "score": 70,
  "scoreBreakdown": {
    "tool-poisoning": 30
  },
  "errors": []
}